winspot/__init__.py
winspot/logger_config.py
winspot/winspot.py
winspot/vendor/__init__.py
winspot/vendor/get_image_size.py
winspot/vendor/licenses/get_image_size.LICENSE.txt
winspot-0.3.1.dist-info/licenses/LICENSE
winspot-0.3.1.dist-info/licenses/src/winspot/vendor/licenses/get_image_size.LICENSE.txt
winspot-0.3.1.dist-info/METADATA
winspot-0.3.1.dist-info/WHEEL
winspot-0.3.1.dist-info/entry_points.txt
winspot-0.3.1.dist-info/top_level.txt
winspot-0.3.1.dist-info/RECORD
