Metadata-Version: 2.4
Name: winspot
Version: 0.3.1
Summary: A CLI utility to extract, download, and reset Windows Spotlight and Bing daily images.
Author: Volodymyr Horshenin
License-Expression: MIT
Project-URL: Repository, https://github.com/l1asis/winspot.git
Project-URL: Issues, https://github.com/l1asis/winspot/issues
Keywords: windows,windows-10,windows-11,windows-spotlight,spotlight,spotlight-images,wallpapers,wallpaper-downloader,desktop-customization,background-images,desktop,lockscreen,cli,utility
Classifier: Development Status :: 4 - Beta
Classifier: Intended Audience :: End Users/Desktop
Classifier: Topic :: Utilities
Classifier: Environment :: Console
Classifier: Operating System :: Microsoft :: Windows
Classifier: Operating System :: Microsoft :: Windows :: Windows 10
Classifier: Operating System :: Microsoft :: Windows :: Windows 11
Classifier: Programming Language :: Python :: 3
Classifier: Programming Language :: Python :: 3.10
Classifier: Programming Language :: Python :: 3.11
Classifier: Programming Language :: Python :: 3.12
Classifier: Programming Language :: Python :: 3.13
Classifier: Programming Language :: Python :: 3.14
Requires-Python: >=3.10
License-File: LICENSE
License-File: src/winspot/vendor/licenses/get_image_size.LICENSE.txt
Provides-Extra: dl
Requires-Dist: requests; extra == "dl"
Dynamic: license-file
